battery_handyman/__init__.py
battery_handyman/__main__.py
battery_handyman/battery_handyman_class.py
battery_handyman/cli.py
battery_handyman/constants.py
battery_handyman/main.py
battery_handyman/util.py
battery_handyman-1.0.0.dist-info/LICENSE
battery_handyman-1.0.0.dist-info/METADATA
battery_handyman-1.0.0.dist-info/WHEEL
battery_handyman-1.0.0.dist-info/top_level.txt
battery_handyman-1.0.0.dist-info/zip-safe
battery_handyman-1.0.0.dist-info/RECORD
