Metadata-Version: 2.1
Name: battery-handyman
Version: 1.0.0
Summary: A customizable battery saving application.
Home-page: https://github.com/NickVeld/battery_handyman
Author: Nikolay Veld
Author-email: novel8mail@gmail.com
License: Apache 2.0
Platform: UNKNOWN
Classifier: Development Status :: 5 - Production/Stable
Classifier: License :: OSI Approved
Classifier: License :: OSI Approved :: Apache Software License
Classifier: Intended Audience :: Developers
Classifier: Intended Audience :: End Users/Desktop
Classifier: Intended Audience :: Other Audience
Classifier: Operating System :: OS Independent
Classifier: Programming Language :: Python
Classifier: Programming Language :: Python :: 3
Classifier: Programming Language :: Python :: 3.7
Classifier: Programming Language :: Python :: 3.8
Classifier: Programming Language :: Python :: 3.9
Classifier: Natural Language :: English
Classifier: Topic :: Desktop Environment
Classifier: Topic :: Home Automation
Classifier: Topic :: System
Classifier: Topic :: System :: Hardware
Classifier: Topic :: Utilities
Requires-Python: >=3.7
Requires-Dist: psutil (>=5.4.2)
Requires-Dist: PyYAML
Requires-Dist: requests (>=0.8.0)
